MANIFEST.in
README.rst
setup.py
googleautoauth/__init__.py
googleautoauth/authorize.py
googleautoauth/auto_auth.py
googleautoauth/client.py
googleautoauth/client_manager.py
googleautoauth/constants.py
googleautoauth/google_authorizer.py
googleautoauth/test_support.py
googleautoauth.egg-info/PKG-INFO
googleautoauth.egg-info/SOURCES.txt
googleautoauth.egg-info/dependency_links.txt
googleautoauth.egg-info/not-zip-safe
googleautoauth.egg-info/requires.txt
googleautoauth.egg-info/top_level.txt
googleautoauth/config/__init__.py
googleautoauth/config/client_manager.py
googleautoauth/config/log.py
googleautoauth/resources/README.rst
googleautoauth/resources/requirements.txt
googleautoauth/resources/version.txt
googleautoauth/resources/scripts/gaa_authorize