Metadata-Version: 1.0
Name: googleautoauth
Version: 0.2.10
Summary: Library to streamline Google authentication from the command-line.
Home-page: https://github.com/dsoprea/python-googleautoauth
Author: Dustin Oprea
Author-email: dustin@randomingenuity.com
License: UNKNOWN
Keywords: google oauth oauth2
Platform: UNKNOWN
